underdoc/__init__.py
underdoc/config.py
underdoc/exceptions.py
underdoc/model.py
underdoc/underdoc_client.py
underdoc/version.py
underdoc-0.4.2.dist-info/licenses/LICENSE
underdoc-0.4.2.dist-info/METADATA
underdoc-0.4.2.dist-info/WHEEL
underdoc-0.4.2.dist-info/top_level.txt
underdoc-0.4.2.dist-info/RECORD
