Metadata-Version: 2.4
Name: underdoc
Version: 0.4.2
Summary: UnderDoc Python SDK
Author-email: Clarence Ho <clarence@underdoc.io>
Project-URL: Homepage, https://github.com/under-doc/underdoc-python-sdk
Classifier: Programming Language :: Python :: 3
Classifier: License :: OSI Approved :: MIT License
Classifier: Operating System :: OS Independent
Requires-Python: >=3.10
License-File: LICENSE
Requires-Dist: pydantic>=2.10.6
Requires-Dist: pydantic-settings>=2.7.1
Requires-Dist: httpx>=0.28.1
Requires-Dist: ray>=2.43.0
Requires-Dist: boto3>=1.37.20
Dynamic: license-file
